[
  {
    "id": 1,
    "name": {
      "english": "Bulbasaur",
      "japanese": "フシギダネ",
      "chinese": "妙蛙种子",
      "french": "Bulbizarre"
    },
    "type": [
      "Grass",
      "Poison"
    ],
    "base": {
      "hp": 45,
      "attack": 49,
      "defense": 49,
      "spAttack": 65,
      "spDefense": 65,
      "Speed": 45
    }
  },
  {
    "id": 2,
    "name": {
      "english": "Ivysaur",
      "japanese": "フシギソウ",
      "chinese": "妙蛙草",
      "french": "Herbizarre"
    },
    "type": [
      "Grass",
      "Poison"
    ],
    "base": {
      "hp": 60,
      "attack": 62,
      "defense": 63,
      "spAttack": 80,
      "spDefense": 80,
      "Speed": 60
    }
  },
  {
    "id": 3,
    "name": {
      "english": "Venusaur",
      "japanese": "フシギバナ",
      "chinese": "妙蛙花",
      "french": "Florizarre"
    },
    "type": [
      "Grass",
      "Poison"
    ],
    "base": {
      "hp": 80,
      "attack": 82,
      "defense": 83,
      "spAttack": 100,
      "spDefense": 100,
      "Speed": 80
    }
  },
  {
    "id": 4,
    "name": {
      "english": "Charmander",
      "japanese": "ヒトカゲ",
      "chinese": "小火龙",
      "french": "Salamèche"
    },
    "type": [
      "Fire"
    ],
    "base": {
      "hp": 39,
      "attack": 52,
      "defense": 43,
      "spAttack": 60,
      "spDefense": 50,
      "Speed": 65
    }
  },
  {
    "id": 5,
    "name": {
      "english": "Charmeleon",
      "japanese": "リザード",
      "chinese": "火恐龙",
      "french": "Reptincel"
    },
    "type": [
      "Fire"
    ],
    "base": {
      "hp": 58,
      "attack": 64,
      "defense": 58,
      "spAttack": 80,
      "spDefense": 65,
      "Speed": 80
    }
  },
  {
    "id": 6,
    "name": {
      "english": "Charizard",
      "japanese": "リザードン",
      "chinese": "喷火龙",
      "french": "Dracaufeu"
    },
    "type": [
      "Fire",
      "Flying"
    ],
    "base": {
      "hp": 78,
      "attack": 84,
      "defense": 78,
      "spAttack": 109,
      "spDefense": 85,
      "Speed": 100
    }
  },
  {
    "id": 7,
    "name": {
      "english": "Squirtle",
      "japanese": "ゼニガメ",
      "chinese": "杰尼龟",
      "french": "Carapuce"
    },
    "type": [
      "Water"
    ],
    "base": {
      "hp": 44,
      "attack": 48,
      "defense": 65,
      "spAttack": 50,
      "spDefense": 64,
      "Speed": 43
    }
  },
  {
    "id": 8,
    "name": {
      "english": "Wartortle",
      "japanese": "カメール",
      "chinese": "卡咪龟",
      "french": "Carabaffe"
    },
    "type": [
      "Water"
    ],
    "base": {
      "hp": 59,
      "attack": 63,
      "defense": 80,
      "spAttack": 65,
      "spDefense": 80,
      "Speed": 58
    }
  },
  {
    "id": 9,
    "name": {
      "english": "Blastoise",
      "japanese": "カメックス",
      "chinese": "水箭龟",
      "french": "Tortank"
    },
    "type": [
      "Water"
    ],
    "base": {
      "hp": 79,
      "attack": 83,
      "defense": 100,
      "spAttack": 85,
      "spDefense": 105,
      "Speed": 78
    }
  },
  {
    "id": 10,
    "name": {
      "english": "Caterpie",
      "japanese": "キャタピー",
      "chinese": "绿毛虫",
      "french": "Chenipan"
    },
    "type": [
      "Bug"
    ],
    "base": {
      "hp": 45,
      "attack": 30,
      "defense": 35,
      "spAttack": 20,
      "spDefense": 20,
      "Speed": 45
    }
  },
  {
    "id": 11,
    "name": {
      "english": "Metapod",
      "japanese": "トランセル",
      "chinese": "铁甲蛹",
      "french": "Chrysacier"
    },
    "type": [
      "Bug"
    ],
    "base": {
      "hp": 50,
      "attack": 20,
      "defense": 55,
      "spAttack": 25,
      "spDefense": 25,
      "Speed": 30
    }
  },
  {
    "id": 12,
    "name": {
      "english": "Butterfree",
      "japanese": "バタフリー",
      "chinese": "巴大蝶",
      "french": "Papilusion"
    },
    "type": [
      "Bug",
      "Flying"
    ],
    "base": {
      "hp": 60,
      "attack": 45,
      "defense": 50,
      "spAttack": 90,
      "spDefense": 80,
      "Speed": 70
    }
  },
  {
    "id": 13,
    "name": {
      "english": "Weedle",
      "japanese": "ビードル",
      "chinese": "独角虫",
      "french": "Aspicot"
    },
    "type": [
      "Bug",
      "Poison"
    ],
    "base": {
      "hp": 40,
      "attack": 35,
      "defense": 30,
      "spAttack": 20,
      "spDefense": 20,
      "Speed": 50
    }
  },
  {
    "id": 14,
    "name": {
      "english": "Kakuna",
      "japanese": "コクーン",
      "chinese": "铁壳蛹",
      "french": "Coconfort"
    },
    "type": [
      "Bug",
      "Poison"
    ],
    "base": {
      "hp": 45,
      "attack": 25,
      "defense": 50,
      "spAttack": 25,
      "spDefense": 25,
      "Speed": 35
    }
  },
  {
    "id": 15,
    "name": {
      "english": "Beedrill",
      "japanese": "スピアー",
      "chinese": "大针蜂",
      "french": "Dardargnan"
    },
    "type": [
      "Bug",
      "Poison"
    ],
    "base": {
      "hp": 65,
      "attack": 90,
      "defense": 40,
      "spAttack": 45,
      "spDefense": 80,
      "Speed": 75
    }
  },
  {
    "id": 16,
    "name": {
      "english": "Pidgey",
      "japanese": "ポッポ",
      "chinese": "波波",
      "french": "Roucool"
    },
    "type": [
      "Normal",
      "Flying"
    ],
    "base": {
      "hp": 40,
      "attack": 45,
      "defense": 40,
      "spAttack": 35,
      "spDefense": 35,
      "Speed": 56
    }
  },
  {
    "id": 17,
    "name": {
      "english": "Pidgeotto",
      "japanese": "ピジョン",
      "chinese": "比比鸟",
      "french": "Roucoups"
    },
    "type": [
      "Normal",
      "Flying"
    ],
    "base": {
      "hp": 63,
      "attack": 60,
      "defense": 55,
      "spAttack": 50,
      "spDefense": 50,
      "Speed": 71
    }
  },
  {
    "id": 18,
    "name": {
      "english": "Pidgeot",
      "japanese": "ピジョット",
      "chinese": "大比鸟",
      "french": "Roucarnage"
    },
    "type": [
      "Normal",
      "Flying"
    ],
    "base": {
      "hp": 83,
      "attack": 80,
      "defense": 75,
      "spAttack": 70,
      "spDefense": 70,
      "Speed": 101
    }
  },
  {
    "id": 19,
    "name": {
      "english": "Rattata",
      "japanese": "コラッタ",
      "chinese": "小拉达",
      "french": "Rattata"
    },
    "type": [
      "Normal"
    ],
    "base": {
      "hp": 30,
      "attack": 56,
      "defense": 35,
      "spAttack": 25,
      "spDefense": 35,
      "Speed": 72
    }
  },
  {
    "id": 20,
    "name": {
      "english": "Raticate",
      "japanese": "ラッタ",
      "chinese": "拉达",
      "french": "Rattatac"
    },
    "type": [
      "Normal"
    ],
    "base": {
      "hp": 55,
      "attack": 81,
      "defense": 60,
      "spAttack": 50,
      "spDefense": 70,
      "Speed": 97
    }
  },
  {
    "id": 21,
    "name": {
      "english": "Spearow",
      "japanese": "オニスズメ",
      "chinese": "烈雀",
      "french": "Piafabec"
    },
    "type": [
      "Normal",
      "Flying"
    ],
    "base": {
      "hp": 40,
      "attack": 60,
      "defense": 30,
      "spAttack": 31,
      "spDefense": 31,
      "Speed": 70
    }
  },
  {
    "id": 22,
    "name": {
      "english": "Fearow",
      "japanese": "オニドリル",
      "chinese": "大嘴雀",
      "french": "Rapasdepic"
    },
    "type": [
      "Normal",
      "Flying"
    ],
    "base": {
      "hp": 65,
      "attack": 90,
      "defense": 65,
      "spAttack": 61,
      "spDefense": 61,
      "Speed": 100
    }
  },
  {
    "id": 23,
    "name": {
      "english": "Ekans",
      "japanese": "アーボ",
      "chinese": "阿柏蛇",
      "french": "Abo"
    },
    "type": [
      "Poison"
    ],
    "base": {
      "hp": 35,
      "attack": 60,
      "defense": 44,
      "spAttack": 40,
      "spDefense": 54,
      "Speed": 55
    }
  },
  {
    "id": 24,
    "name": {
      "english": "Arbok",
      "japanese": "アーボック",
      "chinese": "阿柏怪",
      "french": "Arbok"
    },
    "type": [
      "Poison"
    ],
    "base": {
      "hp": 60,
      "attack": 95,
      "defense": 69,
      "spAttack": 65,
      "spDefense": 79,
      "Speed": 80
    }
  },
  {
    "id": 25,
    "name": {
      "english": "Pikachu",
      "japanese": "ピカチュウ",
      "chinese": "皮卡丘",
      "french": "Pikachu"
    },
    "type": [
      "Electric"
    ],
    "base": {
      "hp": 35,
      "attack": 55,
      "defense": 40,
      "spAttack": 50,
      "spDefense": 50,
      "Speed": 90
    }
  },
  {
    "id": 26,
    "name": {
      "english": "Raichu",
      "japanese": "ライチュウ",
      "chinese": "雷丘",
      "french": "Raichu"
    },
    "type": [
      "Electric"
    ],
    "base": {
      "hp": 60,
      "attack": 90,
      "defense": 55,
      "spAttack": 90,
      "spDefense": 80,
      "Speed": 110
    }
  },
  {
    "id": 27,
    "name": {
      "english": "Sandshrew",
      "japanese": "サンド",
      "chinese": "穿山鼠",
      "french": "Sabelette"
    },
    "type": [
      "Ground"
    ],
    "base": {
      "hp": 50,
      "attack": 75,
      "defense": 85,
      "spAttack": 20,
      "spDefense": 30,
      "Speed": 40
    }
  },
  {
    "id": 28,
    "name": {
      "english": "Sandslash",
      "japanese": "サンドパン",
      "chinese": "穿山王",
      "french": "Sablaireau"
    },
    "type": [
      "Ground"
    ],
    "base": {
      "hp": 75,
      "attack": 100,
      "defense": 110,
      "spAttack": 45,
      "spDefense": 55,
      "Speed": 65
    }
  },
  {
    "id": 29,
    "name": {
      "english": "Nidoran♀",
      "japanese": "ニドラン♀",
      "chinese": "尼多兰",
      "french": "Nidoran♀"
    },
    "type": [
      "Poison"
    ],
    "base": {
      "hp": 55,
      "attack": 47,
      "defense": 52,
      "spAttack": 40,
      "spDefense": 40,
      "Speed": 41
    }
  },
  {
    "id": 30,
    "name": {
      "english": "Nidorina",
      "japanese": "ニドリーナ",
      "chinese": "尼多娜",
      "french": "Nidorina"
    },
    "type": [
      "Poison"
    ],
    "base": {
      "hp": 70,
      "attack": 62,
      "defense": 67,
      "spAttack": 55,
      "spDefense": 55,
      "Speed": 56
    }
  },
  {
    "id": 31,
    "name": {
      "english": "Nidoqueen",
      "japanese": "ニドクイン",
      "chinese": "尼多后",
      "french": "Nidoqueen"
    },
    "type": [
      "Poison",
      "Ground"
    ],
    "base": {
      "hp": 90,
      "attack": 92,
      "defense": 87,
      "spAttack": 75,
      "spDefense": 85,
      "Speed": 76
    }
  },
  {
    "id": 32,
    "name": {
      "english": "Nidoran♂",
      "japanese": "ニドラン♂",
      "chinese": "尼多朗",
      "french": "Nidoran♂"
    },
    "type": [
      "Poison"
    ],
    "base": {
      "hp": 46,
      "attack": 57,
      "defense": 40,
      "spAttack": 40,
      "spDefense": 40,
      "Speed": 50
    }
  },
  {
    "id": 33,
    "name": {
      "english": "Nidorino",
      "japanese": "ニドリーノ",
      "chinese": "尼多力诺",
      "french": "Nidorino"
    },
    "type": [
      "Poison"
    ],
    "base": {
      "hp": 61,
      "attack": 72,
      "defense": 57,
      "spAttack": 55,
      "spDefense": 55,
      "Speed": 65
    }
  },
  {
    "id": 34,
    "name": {
      "english": "Nidoking",
      "japanese": "ニドキング",
      "chinese": "尼多王",
      "french": "Nidoking"
    },
    "type": [
      "Poison",
      "Ground"
    ],
    "base": {
      "hp": 81,
      "attack": 102,
      "defense": 77,
      "spAttack": 85,
      "spDefense": 75,
      "Speed": 85
    }
  },
  {
    "id": 35,
    "name": {
      "english": "Clefairy",
      "japanese": "ピッピ",
      "chinese": "皮皮",
      "french": "Mélofée"
    },
    "type": [
      "Fairy"
    ],
    "base": {
      "hp": 70,
      "attack": 45,
      "defense": 48,
      "spAttack": 60,
      "spDefense": 65,
      "Speed": 35
    }
  },
  {
    "id": 36,
    "name": {
      "english": "Clefable",
      "japanese": "ピクシー",
      "chinese": "皮可西",
      "french": "Mélodelfe"
    },
    "type": [
      "Fairy"
    ],
    "base": {
      "hp": 95,
      "attack": 70,
      "defense": 73,
      "spAttack": 95,
      "spDefense": 90,
      "Speed": 60
    }
  },
  {
    "id": 37,
    "name": {
      "english": "Vulpix",
      "japanese": "ロコン",
      "chinese": "六尾",
      "french": "Goupix"
    },
    "type": [
      "Fire"
    ],
    "base": {
      "hp": 38,
      "attack": 41,
      "defense": 40,
      "spAttack": 50,
      "spDefense": 65,
      "Speed": 65
    }
  },
  {
    "id": 38,
    "name": {
      "english": "Ninetales",
      "japanese": "キュウコン",
      "chinese": "九尾",
      "french": "Feunard"
    },
    "type": [
      "Fire"
    ],
    "base": {
      "hp": 73,
      "attack": 76,
      "defense": 75,
      "spAttack": 81,
      "spDefense": 100,
      "Speed": 100
    }
  },
  {
    "id": 39,
    "name": {
      "english": "Jigglypuff",
      "japanese": "プリン",
      "chinese": "胖丁",
      "french": "Rondoudou"
    },
    "type": [
      "Normal",
      "Fairy"
    ],
    "base": {
      "hp": 115,
      "attack": 45,
      "defense": 20,
      "spAttack": 45,
      "spDefense": 25,
      "Speed": 20
    }
  },
  {
    "id": 40,
    "name": {
      "english": "Wigglytuff",
      "japanese": "プクリン",
      "chinese": "胖可丁",
      "french": "Grodoudou"
    },
    "type": [
      "Normal",
      "Fairy"
    ],
    "base": {
      "hp": 140,
      "attack": 70,
      "defense": 45,
      "spAttack": 85,
      "spDefense": 50,
      "Speed": 45
    }
  },
  {
    "id": 41,
    "name": {
      "english": "Zubat",
      "japanese": "ズバット",
      "chinese": "超音蝠",
      "french": "Nosferapti"
    },
    "type": [
      "Poison",
      "Flying"
    ],
    "base": {
      "hp": 40,
      "attack": 45,
      "defense": 35,
      "spAttack": 30,
      "spDefense": 40,
      "Speed": 55
    }
  },
  {
    "id": 42,
    "name": {
      "english": "Golbat",
      "japanese": "ゴルバット",
      "chinese": "大嘴蝠",
      "french": "Nosferalto"
    },
    "type": [
      "Poison",
      "Flying"
    ],
    "base": {
      "hp": 75,
      "attack": 80,
      "defense": 70,
      "spAttack": 65,
      "spDefense": 75,
      "Speed": 90
    }
  },
  {
    "id": 43,
    "name": {
      "english": "Oddish",
      "japanese": "ナゾノクサ",
      "chinese": "走路草",
      "french": "Mystherbe"
    },
    "type": [
      "Grass",
      "Poison"
    ],
    "base": {
      "hp": 45,
      "attack": 50,
      "defense": 55,
      "spAttack": 75,
      "spDefense": 65,
      "Speed": 30
    }
  },
  {
    "id": 44,
    "name": {
      "english": "Gloom",
      "japanese": "クサイハナ",
      "chinese": "臭臭花",
      "french": "Ortide"
    },
    "type": [
      "Grass",
      "Poison"
    ],
    "base": {
      "hp": 60,
      "attack": 65,
      "defense": 70,
      "spAttack": 85,
      "spDefense": 75,
      "Speed": 40
    }
  },
  {
    "id": 45,
    "name": {
      "english": "Vileplume",
      "japanese": "ラフレシア",
      "chinese": "霸王花",
      "french": "Rafflesia"
    },
    "type": [
      "Grass",
      "Poison"
    ],
    "base": {
      "hp": 75,
      "attack": 80,
      "defense": 85,
      "spAttack": 110,
      "spDefense": 90,
      "Speed": 50
    }
  },
  {
    "id": 46,
    "name": {
      "english": "Paras",
      "japanese": "パラス",
      "chinese": "派拉斯",
      "french": "Paras"
    },
    "type": [
      "Bug",
      "Grass"
    ],
    "base": {
      "hp": 35,
      "attack": 70,
      "defense": 55,
      "spAttack": 45,
      "spDefense": 55,
      "Speed": 25
    }
  },
  {
    "id": 47,
    "name": {
      "english": "Parasect",
      "japanese": "パラセクト",
      "chinese": "派拉斯特",
      "french": "Parasect"
    },
    "type": [
      "Bug",
      "Grass"
    ],
    "base": {
      "hp": 60,
      "attack": 95,
      "defense": 80,
      "spAttack": 60,
      "spDefense": 80,
      "Speed": 30
    }
  },
  {
    "id": 48,
    "name": {
      "english": "Venonat",
      "japanese": "コンパン",
      "chinese": "毛球",
      "french": "Mimitoss"
    },
    "type": [
      "Bug",
      "Poison"
    ],
    "base": {
      "hp": 60,
      "attack": 55,
      "defense": 50,
      "spAttack": 40,
      "spDefense": 55,
      "Speed": 45
    }
  },
  {
    "id": 49,
    "name": {
      "english": "Venomoth",
      "japanese": "モルフォン",
      "chinese": "摩鲁蛾",
      "french": "Aéromite"
    },
    "type": [
      "Bug",
      "Poison"
    ],
    "base": {
      "hp": 70,
      "attack": 65,
      "defense": 60,
      "spAttack": 90,
      "spDefense": 75,
      "Speed": 90
    }
  },
  {
    "id": 50,
    "name": {
      "english": "Diglett",
      "japanese": "ディグダ",
      "chinese": "地鼠",
      "french": "Taupiqueur"
    },
    "type": [
      "Ground"
    ],
    "base": {
      "hp": 10,
      "attack": 55,
      "defense": 25,
      "spAttack": 35,
      "spDefense": 45,
      "Speed": 95
    }
  },
  {
    "id": 51,
    "name": {
      "english": "Dugtrio",
      "japanese": "ダグトリオ",
      "chinese": "三地鼠",
      "french": "Triopikeur"
    },
    "type": [
      "Ground"
    ],
    "base": {
      "hp": 35,
      "attack": 100,
      "defense": 50,
      "spAttack": 50,
      "spDefense": 70,
      "Speed": 120
    }
  },
  {
    "id": 52,
    "name": {
      "english": "Meowth",
      "japanese": "ニャース",
      "chinese": "喵喵",
      "french": "Miaouss"
    },
    "type": [
      "Normal"
    ],
    "base": {
      "hp": 40,
      "attack": 45,
      "defense": 35,
      "spAttack": 40,
      "spDefense": 40,
      "Speed": 90
    }
  },
  {
    "id": 53,
    "name": {
      "english": "Persian",
      "japanese": "ペルシアン",
      "chinese": "猫老大",
      "french": "Persian"
    },
    "type": [
      "Normal"
    ],
    "base": {
      "hp": 65,
      "attack": 70,
      "defense": 60,
      "spAttack": 65,
      "spDefense": 65,
      "Speed": 115
    }
  },
  {
    "id": 54,
    "name": {
      "english": "Psyduck",
      "japanese": "コダック",
      "chinese": "可达鸭",
      "french": "Psykokwak"
    },
    "type": [
      "Water"
    ],
    "base": {
      "hp": 50,
      "attack": 52,
      "defense": 48,
      "spAttack": 65,
      "spDefense": 50,
      "Speed": 55
    }
  },
  {
    "id": 55,
    "name": {
      "english": "Golduck",
      "japanese": "ゴルダック",
      "chinese": "哥达鸭",
      "french": "Akwakwak"
    },
    "type": [
      "Water"
    ],
    "base": {
      "hp": 80,
      "attack": 82,
      "defense": 78,
      "spAttack": 95,
      "spDefense": 80,
      "Speed": 85
    }
  },
  {
    "id": 56,
    "name": {
      "english": "Mankey",
      "japanese": "マンキー",
      "chinese": "猴怪",
      "french": "Férosinge"
    },
    "type": [
      "Fighting"
    ],
    "base": {
      "hp": 40,
      "attack": 80,
      "defense": 35,
      "spAttack": 35,
      "spDefense": 45,
      "Speed": 70
    }
  },
  {
    "id": 57,
    "name": {
      "english": "Primeape",
      "japanese": "オコリザル",
      "chinese": "火暴猴",
      "french": "Colossinge"
    },
    "type": [
      "Fighting"
    ],
    "base": {
      "hp": 65,
      "attack": 105,
      "defense": 60,
      "spAttack": 60,
      "spDefense": 70,
      "Speed": 95
    }
  },
  {
    "id": 58,
    "name": {
      "english": "Growlithe",
      "japanese": "ガーディ",
      "chinese": "卡蒂狗",
      "french": "Caninos"
    },
    "type": [
      "Fire"
    ],
    "base": {
      "hp": 55,
      "attack": 70,
      "defense": 45,
      "spAttack": 70,
      "spDefense": 50,
      "Speed": 60
    }
  },
  {
    "id": 59,
    "name": {
      "english": "Arcanine",
      "japanese": "ウインディ",
      "chinese": "风速狗",
      "french": "Arcanin"
    },
    "type": [
      "Fire"
    ],
    "base": {
      "hp": 90,
      "attack": 110,
      "defense": 80,
      "spAttack": 100,
      "spDefense": 80,
      "Speed": 95
    }
  },
  {
    "id": 60,
    "name": {
      "english": "Poliwag",
      "japanese": "ニョロモ",
      "chinese": "蚊香蝌蚪",
      "french": "Ptitard"
    },
    "type": [
      "Water"
    ],
    "base": {
      "hp": 40,
      "attack": 50,
      "defense": 40,
      "spAttack": 40,
      "spDefense": 40,
      "Speed": 90
    }
  },
  {
    "id": 61,
    "name": {
      "english": "Poliwhirl",
      "japanese": "ニョロゾ",
      "chinese": "蚊香君",
      "french": "Têtarte"
    },
    "type": [
      "Water"
    ],
    "base": {
      "hp": 65,
      "attack": 65,
      "defense": 65,
      "spAttack": 50,
      "spDefense": 50,
      "Speed": 90
    }
  },
  {
    "id": 62,
    "name": {
      "english": "Poliwrath",
      "japanese": "ニョロボン",
      "chinese": "蚊香泳士",
      "french": "Tartard"
    },
    "type": [
      "Water",
      "Fighting"
    ],
    "base": {
      "hp": 90,
      "attack": 95,
      "defense": 95,
      "spAttack": 70,
      "spDefense": 90,
      "Speed": 70
    }
  },
  {
    "id": 63,
    "name": {
      "english": "Abra",
      "japanese": "ケーシィ",
      "chinese": "凯西",
      "french": "Abra"
    },
    "type": [
      "Psychic"
    ],
    "base": {
      "hp": 25,
      "attack": 20,
      "defense": 15,
      "spAttack": 105,
      "spDefense": 55,
      "Speed": 90
    }
  },
  {
    "id": 64,
    "name": {
      "english": "Kadabra",
      "japanese": "ユンゲラー",
      "chinese": "勇基拉",
      "french": "Kadabra"
    },
    "type": [
      "Psychic"
    ],
    "base": {
      "hp": 40,
      "attack": 35,
      "defense": 30,
      "spAttack": 120,
      "spDefense": 70,
      "Speed": 105
    }
  },
  {
    "id": 65,
    "name": {
      "english": "Alakazam",
      "japanese": "フーディン",
      "chinese": "胡地",
      "french": "Alakazam"
    },
    "type": [
      "Psychic"
    ],
    "base": {
      "hp": 55,
      "attack": 50,
      "defense": 45,
      "spAttack": 135,
      "spDefense": 95,
      "Speed": 120
    }
  },
  {
    "id": 66,
    "name": {
      "english": "Machop",
      "japanese": "ワンリキー",
      "chinese": "腕力",
      "french": "Machoc"
    },
    "type": [
      "Fighting"
    ],
    "base": {
      "hp": 70,
      "attack": 80,
      "defense": 50,
      "spAttack": 35,
      "spDefense": 35,
      "Speed": 35
    }
  },
  {
    "id": 67,
    "name": {
      "english": "Machoke",
      "japanese": "ゴーリキー",
      "chinese": "豪力",
      "french": "Machopeur"
    },
    "type": [
      "Fighting"
    ],
    "base": {
      "hp": 80,
      "attack": 100,
      "defense": 70,
      "spAttack": 50,
      "spDefense": 60,
      "Speed": 45
    }
  },
  {
    "id": 68,
    "name": {
      "english": "Machamp",
      "japanese": "カイリキー",
      "chinese": "怪力",
      "french": "Mackogneur"
    },
    "type": [
      "Fighting"
    ],
    "base": {
      "hp": 90,
      "attack": 130,
      "defense": 80,
      "spAttack": 65,
      "spDefense": 85,
      "Speed": 55
    }
  },
  {
    "id": 69,
    "name": {
      "english": "Bellsprout",
      "japanese": "マダツボミ",
      "chinese": "喇叭芽",
      "french": "Chétiflor"
    },
    "type": [
      "Grass",
      "Poison"
    ],
    "base": {
      "hp": 50,
      "attack": 75,
      "defense": 35,
      "spAttack": 70,
      "spDefense": 30,
      "Speed": 40
    }
  },
  {
    "id": 70,
    "name": {
      "english": "Weepinbell",
      "japanese": "ウツドン",
      "chinese": "口呆花",
      "french": "Boustiflor"
    },
    "type": [
      "Grass",
      "Poison"
    ],
    "base": {
      "hp": 65,
      "attack": 90,
      "defense": 50,
      "spAttack": 85,
      "spDefense": 45,
      "Speed": 55
    }
  },
  {
    "id": 71,
    "name": {
      "english": "Victreebel",
      "japanese": "ウツボット",
      "chinese": "大食花",
      "french": "Empiflor"
    },
    "type": [
      "Grass",
      "Poison"
    ],
    "base": {
      "hp": 80,
      "attack": 105,
      "defense": 65,
      "spAttack": 100,
      "spDefense": 70,
      "Speed": 70
    }
  },
  {
    "id": 72,
    "name": {
      "english": "Tentacool",
      "japanese": "メノクラゲ",
      "chinese": "玛瑙水母",
      "french": "Tentacool"
    },
    "type": [
      "Water",
      "Poison"
    ],
    "base": {
      "hp": 40,
      "attack": 40,
      "defense": 35,
      "spAttack": 50,
      "spDefense": 100,
      "Speed": 70
    }
  },
  {
    "id": 73,
    "name": {
      "english": "Tentacruel",
      "japanese": "ドククラゲ",
      "chinese": "毒刺水母",
      "french": "Tentacruel"
    },
    "type": [
      "Water",
      "Poison"
    ],
    "base": {
      "hp": 80,
      "attack": 70,
      "defense": 65,
      "spAttack": 80,
      "spDefense": 120,
      "Speed": 100
    }
  },
  {
    "id": 74,
    "name": {
      "english": "Geodude",
      "japanese": "イシツブテ",
      "chinese": "小拳石",
      "french": "Racaillou"
    },
    "type": [
      "Rock",
      "Ground"
    ],
    "base": {
      "hp": 40,
      "attack": 80,
      "defense": 100,
      "spAttack": 30,
      "spDefense": 30,
      "Speed": 20
    }
  },
  {
    "id": 75,
    "name": {
      "english": "Graveler",
      "japanese": "ゴローン",
      "chinese": "隆隆石",
      "french": "Gravalanch"
    },
    "type": [
      "Rock",
      "Ground"
    ],
    "base": {
      "hp": 55,
      "attack": 95,
      "defense": 115,
      "spAttack": 45,
      "spDefense": 45,
      "Speed": 35
    }
  },
  {
    "id": 76,
    "name": {
      "english": "Golem",
      "japanese": "ゴローニャ",
      "chinese": "隆隆岩",
      "french": "Grolem"
    },
    "type": [
      "Rock",
      "Ground"
    ],
    "base": {
      "hp": 80,
      "attack": 120,
      "defense": 130,
      "spAttack": 55,
      "spDefense": 65,
      "Speed": 45
    }
  },
  {
    "id": 77,
    "name": {
      "english": "Ponyta",
      "japanese": "ポニータ",
      "chinese": "小火马",
      "french": "Ponyta"
    },
    "type": [
      "Fire"
    ],
    "base": {
      "hp": 50,
      "attack": 85,
      "defense": 55,
      "spAttack": 65,
      "spDefense": 65,
      "Speed": 90
    }
  },
  {
    "id": 78,
    "name": {
      "english": "Rapidash",
      "japanese": "ギャロップ",
      "chinese": "烈焰马",
      "french": "Galopa"
    },
    "type": [
      "Fire"
    ],
    "base": {
      "hp": 65,
      "attack": 100,
      "defense": 70,
      "spAttack": 80,
      "spDefense": 80,
      "Speed": 105
    }
  },
  {
    "id": 79,
    "name": {
      "english": "Slowpoke",
      "japanese": "ヤドン",
      "chinese": "呆呆兽",
      "french": "Ramoloss"
    },
    "type": [
      "Water",
      "Psychic"
    ],
    "base": {
      "hp": 90,
      "attack": 65,
      "defense": 65,
      "spAttack": 40,
      "spDefense": 40,
      "Speed": 15
    }
  },
  {
    "id": 80,
    "name": {
      "english": "Slowbro",
      "japanese": "ヤドラン",
      "chinese": "呆壳兽",
      "french": "Flagadoss"
    },
    "type": [
      "Water",
      "Psychic"
    ],
    "base": {
      "hp": 95,
      "attack": 75,
      "defense": 110,
      "spAttack": 100,
      "spDefense": 80,
      "Speed": 30
    }
  },
  {
    "id": 81,
    "name": {
      "english": "Magnemite",
      "japanese": "コイル",
      "chinese": "小磁怪",
      "french": "Magnéti"
    },
    "type": [
      "Electric",
      "Steel"
    ],
    "base": {
      "hp": 25,
      "attack": 35,
      "defense": 70,
      "spAttack": 95,
      "spDefense": 55,
      "Speed": 45
    }
  },
  {
    "id": 82,
    "name": {
      "english": "Magneton",
      "japanese": "レアコイル",
      "chinese": "三合一磁怪",
      "french": "Magnéton"
    },
    "type": [
      "Electric",
      "Steel"
    ],
    "base": {
      "hp": 50,
      "attack": 60,
      "defense": 95,
      "spAttack": 120,
      "spDefense": 70,
      "Speed": 70
    }
  },
  {
    "id": 83,
    "name": {
      "english": "Farfetch'd",
      "japanese": "カモネギ",
      "chinese": "大葱鸭",
      "french": "Canarticho"
    },
    "type": [
      "Normal",
      "Flying"
    ],
    "base": {
      "hp": 52,
      "attack": 90,
      "defense": 55,
      "spAttack": 58,
      "spDefense": 62,
      "Speed": 60
    }
  },
  {
    "id": 84,
    "name": {
      "english": "Doduo",
      "japanese": "ドードー",
      "chinese": "嘟嘟",
      "french": "Doduo"
    },
    "type": [
      "Normal",
      "Flying"
    ],
    "base": {
      "hp": 35,
      "attack": 85,
      "defense": 45,
      "spAttack": 35,
      "spDefense": 35,
      "Speed": 75
    }
  },
  {
    "id": 85,
    "name": {
      "english": "Dodrio",
      "japanese": "ドードリオ",
      "chinese": "嘟嘟利",
      "french": "Dodrio"
    },
    "type": [
      "Normal",
      "Flying"
    ],
    "base": {
      "hp": 60,
      "attack": 110,
      "defense": 70,
      "spAttack": 60,
      "spDefense": 60,
      "Speed": 110
    }
  },
  {
    "id": 86,
    "name": {
      "english": "Seel",
      "japanese": "パウワウ",
      "chinese": "小海狮",
      "french": "Otaria"
    },
    "type": [
      "Water"
    ],
    "base": {
      "hp": 65,
      "attack": 45,
      "defense": 55,
      "spAttack": 45,
      "spDefense": 70,
      "Speed": 45
    }
  },
  {
    "id": 87,
    "name": {
      "english": "Dewgong",
      "japanese": "ジュゴン",
      "chinese": "白海狮",
      "french": "Lamantine"
    },
    "type": [
      "Water",
      "Ice"
    ],
    "base": {
      "hp": 90,
      "attack": 70,
      "defense": 80,
      "spAttack": 70,
      "spDefense": 95,
      "Speed": 70
    }
  },
  {
    "id": 88,
    "name": {
      "english": "Grimer",
      "japanese": "ベトベター",
      "chinese": "臭泥",
      "french": "Tadmorv"
    },
    "type": [
      "Poison"
    ],
    "base": {
      "hp": 80,
      "attack": 80,
      "defense": 50,
      "spAttack": 40,
      "spDefense": 50,
      "Speed": 25
    }
  },
  {
    "id": 89,
    "name": {
      "english": "Muk",
      "japanese": "ベトベトン",
      "chinese": "臭臭泥",
      "french": "Grotadmorv"
    },
    "type": [
      "Poison"
    ],
    "base": {
      "hp": 105,
      "attack": 105,
      "defense": 75,
      "spAttack": 65,
      "spDefense": 100,
      "Speed": 50
    }
  },
  {
    "id": 90,
    "name": {
      "english": "Shellder",
      "japanese": "シェルダー",
      "chinese": "大舌贝",
      "french": "Kokiyas"
    },
    "type": [
      "Water"
    ],
    "base": {
      "hp": 30,
      "attack": 65,
      "defense": 100,
      "spAttack": 45,
      "spDefense": 25,
      "Speed": 40
    }
  },
  {
    "id": 91,
    "name": {
      "english": "Cloyster",
      "japanese": "パルシェン",
      "chinese": "刺甲贝",
      "french": "Crustabri"
    },
    "type": [
      "Water",
      "Ice"
    ],
    "base": {
      "hp": 50,
      "attack": 95,
      "defense": 180,
      "spAttack": 85,
      "spDefense": 45,
      "Speed": 70
    }
  },
  {
    "id": 92,
    "name": {
      "english": "Gastly",
      "japanese": "ゴース",
      "chinese": "鬼斯",
      "french": "Fantominus"
    },
    "type": [
      "Ghost",
      "Poison"
    ],
    "base": {
      "hp": 30,
      "attack": 35,
      "defense": 30,
      "spAttack": 100,
      "spDefense": 35,
      "Speed": 80
    }
  },
  {
    "id": 93,
    "name": {
      "english": "Haunter",
      "japanese": "ゴースト",
      "chinese": "鬼斯通",
      "french": "Spectrum"
    },
    "type": [
      "Ghost",
      "Poison"
    ],
    "base": {
      "hp": 45,
      "attack": 50,
      "defense": 45,
      "spAttack": 115,
      "spDefense": 55,
      "Speed": 95
    }
  },
  {
    "id": 94,
    "name": {
      "english": "Gengar",
      "japanese": "ゲンガー",
      "chinese": "耿鬼",
      "french": "Ectoplasma"
    },
    "type": [
      "Ghost",
      "Poison"
    ],
    "base": {
      "hp": 60,
      "attack": 65,
      "defense": 60,
      "spAttack": 130,
      "spDefense": 75,
      "Speed": 110
    }
  },
  {
    "id": 95,
    "name": {
      "english": "Onix",
      "japanese": "イワーク",
      "chinese": "大岩蛇",
      "french": "Onix"
    },
    "type": [
      "Rock",
      "Ground"
    ],
    "base": {
      "hp": 35,
      "attack": 45,
      "defense": 160,
      "spAttack": 30,
      "spDefense": 45,
      "Speed": 70
    }
  },
  {
    "id": 96,
    "name": {
      "english": "Drowzee",
      "japanese": "スリープ",
      "chinese": "催眠貘",
      "french": "Soporifik"
    },
    "type": [
      "Psychic"
    ],
    "base": {
      "hp": 60,
      "attack": 48,
      "defense": 45,
      "spAttack": 43,
      "spDefense": 90,
      "Speed": 42
    }
  },
  {
    "id": 97,
    "name": {
      "english": "Hypno",
      "japanese": "スリーパー",
      "chinese": "引梦貘人",
      "french": "Hypnomade"
    },
    "type": [
      "Psychic"
    ],
    "base": {
      "hp": 85,
      "attack": 73,
      "defense": 70,
      "spAttack": 73,
      "spDefense": 115,
      "Speed": 67
    }
  },
  {
    "id": 98,
    "name": {
      "english": "Krabby",
      "japanese": "クラブ",
      "chinese": "大钳蟹",
      "french": "Krabby"
    },
    "type": [
      "Water"
    ],
    "base": {
      "hp": 30,
      "attack": 105,
      "defense": 90,
      "spAttack": 25,
      "spDefense": 25,
      "Speed": 50
    }
  },
  {
    "id": 99,
    "name": {
      "english": "Kingler",
      "japanese": "キングラー",
      "chinese": "巨钳蟹",
      "french": "Krabboss"
    },
    "type": [
      "Water"
    ],
    "base": {
      "hp": 55,
      "attack": 130,
      "defense": 115,
      "spAttack": 50,
      "spDefense": 50,
      "Speed": 75
    }
  },
  {
    "id": 100,
    "name": {
      "english": "Voltorb",
      "japanese": "ビリリダマ",
      "chinese": "霹雳电球",
      "french": "Voltorbe"
    },
    "type": [
      "Electric"
    ],
    "base": {
      "hp": 40,
      "attack": 30,
      "defense": 50,
      "spAttack": 55,
      "spDefense": 55,
      "Speed": 100
    }
  },
  {
    "id": 101,
    "name": {
      "english": "Electrode",
      "japanese": "マルマイン",
      "chinese": "顽皮雷弹",
      "french": "Électrode"
    },
    "type": [
      "Electric"
    ],
    "base": {
      "hp": 60,
      "attack": 50,
      "defense": 70,
      "spAttack": 80,
      "spDefense": 80,
      "Speed": 150
    }
  },
  {
    "id": 102,
    "name": {
      "english": "Exeggcute",
      "japanese": "タマタマ",
      "chinese": "蛋蛋",
      "french": "Noeunoeuf"
    },
    "type": [
      "Grass",
      "Psychic"
    ],
    "base": {
      "hp": 60,
      "attack": 40,
      "defense": 80,
      "spAttack": 60,
      "spDefense": 45,
      "Speed": 40
    }
  },
  {
    "id": 103,
    "name": {
      "english": "Exeggutor",
      "japanese": "ナッシー",
      "chinese": "椰蛋树",
      "french": "Noadkoko"
    },
    "type": [
      "Grass",
      "Psychic"
    ],
    "base": {
      "hp": 95,
      "attack": 95,
      "defense": 85,
      "spAttack": 125,
      "spDefense": 75,
      "Speed": 55
    }
  },
  {
    "id": 104,
    "name": {
      "english": "Cubone",
      "japanese": "カラカラ",
      "chinese": "卡拉卡拉",
      "french": "Osselait"
    },
    "type": [
      "Ground"
    ],
    "base": {
      "hp": 50,
      "attack": 50,
      "defense": 95,
      "spAttack": 40,
      "spDefense": 50,
      "Speed": 35
    }
  },
  {
    "id": 105,
    "name": {
      "english": "Marowak",
      "japanese": "ガラガラ",
      "chinese": "嘎啦嘎啦",
      "french": "Ossatueur"
    },
    "type": [
      "Ground"
    ],
    "base": {
      "hp": 60,
      "attack": 80,
      "defense": 110,
      "spAttack": 50,
      "spDefense": 80,
      "Speed": 45
    }
  },
  {
    "id": 106,
    "name": {
      "english": "Hitmonlee",
      "japanese": "サワムラー",
      "chinese": "飞腿郎",
      "french": "Kicklee"
    },
    "type": [
      "Fighting"
    ],
    "base": {
      "hp": 50,
      "attack": 120,
      "defense": 53,
      "spAttack": 35,
      "spDefense": 110,
      "Speed": 87
    }
  },
  {
    "id": 107,
    "name": {
      "english": "Hitmonchan",
      "japanese": "エビワラー",
      "chinese": "快拳郎",
      "french": "Tygnon"
    },
    "type": [
      "Fighting"
    ],
    "base": {
      "hp": 50,
      "attack": 105,
      "defense": 79,
      "spAttack": 35,
      "spDefense": 110,
      "Speed": 76
    }
  },
  {
    "id": 108,
    "name": {
      "english": "Lickitung",
      "japanese": "ベロリンガ",
      "chinese": "大舌头",
      "french": "Excelangue"
    },
    "type": [
      "Normal"
    ],
    "base": {
      "hp": 90,
      "attack": 55,
      "defense": 75,
      "spAttack": 60,
      "spDefense": 75,
      "Speed": 30
    }
  },
  {
    "id": 109,
    "name": {
      "english": "Koffing",
      "japanese": "ドガース",
      "chinese": "瓦斯弹",
      "french": "Smogo"
    },
    "type": [
      "Poison"
    ],
    "base": {
      "hp": 40,
      "attack": 65,
      "defense": 95,
      "spAttack": 60,
      "spDefense": 45,
      "Speed": 35
    }
  },
  {
    "id": 110,
    "name": {
      "english": "Weezing",
      "japanese": "マタドガス",
      "chinese": "双弹瓦斯",
      "french": "Smogogo"
    },
    "type": [
      "Poison"
    ],
    "base": {
      "hp": 65,
      "attack": 90,
      "defense": 120,
      "spAttack": 85,
      "spDefense": 70,
      "Speed": 60
    }
  },
  {
    "id": 111,
    "name": {
      "english": "Rhyhorn",
      "japanese": "サイホーン",
      "chinese": "独角犀牛",
      "french": "Rhinocorne"
    },
    "type": [
      "Ground",
      "Rock"
    ],
    "base": {
      "hp": 80,
      "attack": 85,
      "defense": 95,
      "spAttack": 30,
      "spDefense": 30,
      "Speed": 25
    }
  },
  {
    "id": 112,
    "name": {
      "english": "Rhydon",
      "japanese": "サイドン",
      "chinese": "钻角犀兽",
      "french": "Rhinoféros"
    },
    "type": [
      "Ground",
      "Rock"
    ],
    "base": {
      "hp": 105,
      "attack": 130,
      "defense": 120,
      "spAttack": 45,
      "spDefense": 45,
      "Speed": 40
    }
  },
  {
    "id": 113,
    "name": {
      "english": "Chansey",
      "japanese": "ラッキー",
      "chinese": "吉利蛋",
      "french": "Leveinard"
    },
    "type": [
      "Normal"
    ],
    "base": {
      "hp": 250,
      "attack": 5,
      "defense": 5,
      "spAttack": 35,
      "spDefense": 105,
      "Speed": 50
    }
  },
  {
    "id": 114,
    "name": {
      "english": "Tangela",
      "japanese": "モンジャラ",
      "chinese": "蔓藤怪",
      "french": "Saquedeneu"
    },
    "type": [
      "Grass"
    ],
    "base": {
      "hp": 65,
      "attack": 55,
      "defense": 115,
      "spAttack": 100,
      "spDefense": 40,
      "Speed": 60
    }
  },
  {
    "id": 115,
    "name": {
      "english": "Kangaskhan",
      "japanese": "ガルーラ",
      "chinese": "袋兽",
      "french": "Kangourex"
    },
    "type": [
      "Normal"
    ],
    "base": {
      "hp": 105,
      "attack": 95,
      "defense": 80,
      "spAttack": 40,
      "spDefense": 80,
      "Speed": 90
    }
  },
  {
    "id": 116,
    "name": {
      "english": "Horsea",
      "japanese": "タッツー",
      "chinese": "墨海马",
      "french": "Hypotrempe"
    },
    "type": [
      "Water"
    ],
    "base": {
      "hp": 30,
      "attack": 40,
      "defense": 70,
      "spAttack": 70,
      "spDefense": 25,
      "Speed": 60
    }
  },
  {
    "id": 117,
    "name": {
      "english": "Seadra",
      "japanese": "シードラ",
      "chinese": "海刺龙",
      "french": "Hypocéan"
    },
    "type": [
      "Water"
    ],
    "base": {
      "hp": 55,
      "attack": 65,
      "defense": 95,
      "spAttack": 95,
      "spDefense": 45,
      "Speed": 85
    }
  },
  {
    "id": 118,
    "name": {
      "english": "Goldeen",
      "japanese": "トサキント",
      "chinese": "角金鱼",
      "french": "Poissirène"
    },
    "type": [
      "Water"
    ],
    "base": {
      "hp": 45,
      "attack": 67,
      "defense": 60,
      "spAttack": 35,
      "spDefense": 50,
      "Speed": 63
    }
  },
  {
    "id": 119,
    "name": {
      "english": "Seaking",
      "japanese": "アズマオウ",
      "chinese": "金鱼王",
      "french": "Poissoroy"
    },
    "type": [
      "Water"
    ],
    "base": {
      "hp": 80,
      "attack": 92,
      "defense": 65,
      "spAttack": 65,
      "spDefense": 80,
      "Speed": 68
    }
  },
  {
    "id": 120,
    "name": {
      "english": "Staryu",
      "japanese": "ヒトデマン",
      "chinese": "海星星",
      "french": "Stari"
    },
    "type": [
      "Water"
    ],
    "base": {
      "hp": 30,
      "attack": 45,
      "defense": 55,
      "spAttack": 70,
      "spDefense": 55,
      "Speed": 85
    }
  },
  {
    "id": 121,
    "name": {
      "english": "Starmie",
      "japanese": "スターミー",
      "chinese": "宝石海星",
      "french": "Staross"
    },
    "type": [
      "Water",
      "Psychic"
    ],
    "base": {
      "hp": 60,
      "attack": 75,
      "defense": 85,
      "spAttack": 100,
      "spDefense": 85,
      "Speed": 115
    }
  },
  {
    "id": 122,
    "name": {
      "english": "Mr. Mime",
      "japanese": "バリヤード",
      "chinese": "魔墙人偶",
      "french": "M. Mime"
    },
    "type": [
      "Psychic",
      "Fairy"
    ],
    "base": {
      "hp": 40,
      "attack": 45,
      "defense": 65,
      "spAttack": 100,
      "spDefense": 120,
      "Speed": 90
    }
  },
  {
    "id": 123,
    "name": {
      "english": "Scyther",
      "japanese": "ストライク",
      "chinese": "飞天螳螂",
      "french": "Insécateur"
    },
    "type": [
      "Bug",
      "Flying"
    ],
    "base": {
      "hp": 70,
      "attack": 110,
      "defense": 80,
      "spAttack": 55,
      "spDefense": 80,
      "Speed": 105
    }
  },
  {
    "id": 124,
    "name": {
      "english": "Jynx",
      "japanese": "ルージュラ",
      "chinese": "迷唇姐",
      "french": "Lippoutou"
    },
    "type": [
      "Ice",
      "Psychic"
    ],
    "base": {
      "hp": 65,
      "attack": 50,
      "defense": 35,
      "spAttack": 115,
      "spDefense": 95,
      "Speed": 95
    }
  },
  {
    "id": 125,
    "name": {
      "english": "Electabuzz",
      "japanese": "エレブー",
      "chinese": "电击兽",
      "french": "Élektek"
    },
    "type": [
      "Electric"
    ],
    "base": {
      "hp": 65,
      "attack": 83,
      "defense": 57,
      "spAttack": 95,
      "spDefense": 85,
      "Speed": 105
    }
  },
  {
    "id": 126,
    "name": {
      "english": "Magmar",
      "japanese": "ブーバー",
      "chinese": "鸭嘴火兽",
      "french": "Magmar"
    },
    "type": [
      "Fire"
    ],
    "base": {
      "hp": 65,
      "attack": 95,
      "defense": 57,
      "spAttack": 100,
      "spDefense": 85,
      "Speed": 93
    }
  },
  {
    "id": 127,
    "name": {
      "english": "Pinsir",
      "japanese": "カイロス",
      "chinese": "凯罗斯",
      "french": "Scarabrute"
    },
    "type": [
      "Bug"
    ],
    "base": {
      "hp": 65,
      "attack": 125,
      "defense": 100,
      "spAttack": 55,
      "spDefense": 70,
      "Speed": 85
    }
  },
  {
    "id": 128,
    "name": {
      "english": "Tauros",
      "japanese": "ケンタロス",
      "chinese": "肯泰罗",
      "french": "Tauros"
    },
    "type": [
      "Normal"
    ],
    "base": {
      "hp": 75,
      "attack": 100,
      "defense": 95,
      "spAttack": 40,
      "spDefense": 70,
      "Speed": 110
    }
  },
  {
    "id": 129,
    "name": {
      "english": "Magikarp",
      "japanese": "コイキング",
      "chinese": "鲤鱼王",
      "french": "Magicarpe"
    },
    "type": [
      "Water"
    ],
    "base": {
      "hp": 20,
      "attack": 10,
      "defense": 55,
      "spAttack": 15,
      "spDefense": 20,
      "Speed": 80
    }
  },
  {
    "id": 130,
    "name": {
      "english": "Gyarados",
      "japanese": "ギャラドス",
      "chinese": "暴鲤龙",
      "french": "Léviator"
    },
    "type": [
      "Water",
      "Flying"
    ],
    "base": {
      "hp": 95,
      "attack": 125,
      "defense": 79,
      "spAttack": 60,
      "spDefense": 100,
      "Speed": 81
    }
  },
  {
    "id": 131,
    "name": {
      "english": "Lapras",
      "japanese": "ラプラス",
      "chinese": "拉普拉斯",
      "french": "Lokhlass"
    },
    "type": [
      "Water",
      "Ice"
    ],
    "base": {
      "hp": 130,
      "attack": 85,
      "defense": 80,
      "spAttack": 85,
      "spDefense": 95,
      "Speed": 60
    }
  },
  {
    "id": 132,
    "name": {
      "english": "Ditto",
      "japanese": "メタモン",
      "chinese": "百变怪",
      "french": "Métamorph"
    },
    "type": [
      "Normal"
    ],
    "base": {
      "hp": 48,
      "attack": 48,
      "defense": 48,
      "spAttack": 48,
      "spDefense": 48,
      "Speed": 48
    }
  },
  {
    "id": 133,
    "name": {
      "english": "Eevee",
      "japanese": "イーブイ",
      "chinese": "伊布",
      "french": "Évoli"
    },
    "type": [
      "Normal"
    ],
    "base": {
      "hp": 55,
      "attack": 55,
      "defense": 50,
      "spAttack": 45,
      "spDefense": 65,
      "Speed": 55
    }
  },
  {
    "id": 134,
    "name": {
      "english": "Vaporeon",
      "japanese": "シャワーズ",
      "chinese": "水伊布",
      "french": "Aquali"
    },
    "type": [
      "Water"
    ],
    "base": {
      "hp": 130,
      "attack": 65,
      "defense": 60,
      "spAttack": 110,
      "spDefense": 95,
      "Speed": 65
    }
  },
  {
    "id": 135,
    "name": {
      "english": "Jolteon",
      "japanese": "サンダース",
      "chinese": "雷伊布",
      "french": "Voltali"
    },
    "type": [
      "Electric"
    ],
    "base": {
      "hp": 65,
      "attack": 65,
      "defense": 60,
      "spAttack": 110,
      "spDefense": 95,
      "Speed": 130
    }
  },
  {
    "id": 136,
    "name": {
      "english": "Flareon",
      "japanese": "ブースター",
      "chinese": "火伊布",
      "french": "Pyroli"
    },
    "type": [
      "Fire"
    ],
    "base": {
      "hp": 65,
      "attack": 130,
      "defense": 60,
      "spAttack": 95,
      "spDefense": 110,
      "Speed": 65
    }
  },
  {
    "id": 137,
    "name": {
      "english": "Porygon",
      "japanese": "ポリゴン",
      "chinese": "多边兽",
      "french": "Porygon"
    },
    "type": [
      "Normal"
    ],
    "base": {
      "hp": 65,
      "attack": 60,
      "defense": 70,
      "spAttack": 85,
      "spDefense": 75,
      "Speed": 40
    }
  },
  {
    "id": 138,
    "name": {
      "english": "Omanyte",
      "japanese": "オムナイト",
      "chinese": "菊石兽",
      "french": "Amonita"
    },
    "type": [
      "Rock",
      "Water"
    ],
    "base": {
      "hp": 35,
      "attack": 40,
      "defense": 100,
      "spAttack": 90,
      "spDefense": 55,
      "Speed": 35
    }
  },
  {
    "id": 139,
    "name": {
      "english": "Omastar",
      "japanese": "オムスター",
      "chinese": "多刺菊石兽",
      "french": "Amonistar"
    },
    "type": [
      "Rock",
      "Water"
    ],
    "base": {
      "hp": 70,
      "attack": 60,
      "defense": 125,
      "spAttack": 115,
      "spDefense": 70,
      "Speed": 55
    }
  },
  {
    "id": 140,
    "name": {
      "english": "Kabuto",
      "japanese": "カブト",
      "chinese": "化石盔",
      "french": "Kabuto"
    },
    "type": [
      "Rock",
      "Water"
    ],
    "base": {
      "hp": 30,
      "attack": 80,
      "defense": 90,
      "spAttack": 55,
      "spDefense": 45,
      "Speed": 55
    }
  },
  {
    "id": 141,
    "name": {
      "english": "Kabutops",
      "japanese": "カブトプス",
      "chinese": "镰刀盔",
      "french": "Kabutops"
    },
    "type": [
      "Rock",
      "Water"
    ],
    "base": {
      "hp": 60,
      "attack": 115,
      "defense": 105,
      "spAttack": 65,
      "spDefense": 70,
      "Speed": 80
    }
  },
  {
    "id": 142,
    "name": {
      "english": "Aerodactyl",
      "japanese": "プテラ",
      "chinese": "化石翼龙",
      "french": "Ptéra"
    },
    "type": [
      "Rock",
      "Flying"
    ],
    "base": {
      "hp": 80,
      "attack": 105,
      "defense": 65,
      "spAttack": 60,
      "spDefense": 75,
      "Speed": 130
    }
  },
  {
    "id": 143,
    "name": {
      "english": "Snorlax",
      "japanese": "カビゴン",
      "chinese": "卡比兽",
      "french": "Ronflex"
    },
    "type": [
      "Normal"
    ],
    "base": {
      "hp": 160,
      "attack": 110,
      "defense": 65,
      "spAttack": 65,
      "spDefense": 110,
      "Speed": 30
    }
  },
  {
    "id": 144,
    "name": {
      "english": "Articuno",
      "japanese": "フリーザー",
      "chinese": "急冻鸟",
      "french": "Artikodin"
    },
    "type": [
      "Ice",
      "Flying"
    ],
    "base": {
      "hp": 90,
      "attack": 85,
      "defense": 100,
      "spAttack": 95,
      "spDefense": 125,
      "Speed": 85
    }
  },
  {
    "id": 145,
    "name": {
      "english": "Zapdos",
      "japanese": "サンダー",
      "chinese": "闪电鸟",
      "french": "Électhor"
    },
    "type": [
      "Electric",
      "Flying"
    ],
    "base": {
      "hp": 90,
      "attack": 90,
      "defense": 85,
      "spAttack": 125,
      "spDefense": 90,
      "Speed": 100
    }
  },
  {
    "id": 146,
    "name": {
      "english": "Moltres",
      "japanese": "ファイヤー",
      "chinese": "火焰鸟",
      "french": "Sulfura"
    },
    "type": [
      "Fire",
      "Flying"
    ],
    "base": {
      "hp": 90,
      "attack": 100,
      "defense": 90,
      "spAttack": 125,
      "spDefense": 85,
      "Speed": 90
    }
  },
  {
    "id": 147,
    "name": {
      "english": "Dratini",
      "japanese": "ミニリュウ",
      "chinese": "迷你龙",
      "french": "Minidraco"
    },
    "type": [
      "Dragon"
    ],
    "base": {
      "hp": 41,
      "attack": 64,
      "defense": 45,
      "spAttack": 50,
      "spDefense": 50,
      "Speed": 50
    }
  },
  {
    "id": 148,
    "name": {
      "english": "Dragonair",
      "japanese": "ハクリュー",
      "chinese": "哈克龙",
      "french": "Draco"
    },
    "type": [
      "Dragon"
    ],
    "base": {
      "hp": 61,
      "attack": 84,
      "defense": 65,
      "spAttack": 70,
      "spDefense": 70,
      "Speed": 70
    }
  },
  {
    "id": 149,
    "name": {
      "english": "Dragonite",
      "japanese": "カイリュー",
      "chinese": "快龙",
      "french": "Dracolosse"
    },
    "type": [
      "Dragon",
      "Flying"
    ],
    "base": {
      "hp": 91,
      "attack": 134,
      "defense": 95,
      "spAttack": 100,
      "spDefense": 100,
      "Speed": 80
    }
  },
  {
    "id": 150,
    "name": {
      "english": "Mewtwo",
      "japanese": "ミュウツー",
      "chinese": "超梦",
      "french": "Mewtwo"
    },
    "type": [
      "Psychic"
    ],
    "base": {
      "hp": 106,
      "attack": 110,
      "defense": 90,
      "spAttack": 154,
      "spDefense": 90,
      "Speed": 130
    }
  },
  {
    "id": 151,
    "name": {
      "english": "Mew",
      "japanese": "ミュウ",
      "chinese": "梦幻",
      "french": "Mew"
    },
    "type": [
      "Psychic"
    ],
    "base": {
      "hp": 100,
      "attack": 100,
      "defense": 100,
      "spAttack": 100,
      "spDefense": 100,
      "Speed": 100
    }
  }
]